kleborate/__init__.py
kleborate/__main__.py
kleborate/version.py
kleborate/modules/__init__.py
kleborate/modules/enterobacterales__species/__init__.py
kleborate/modules/enterobacterales__species/enterobacterales__species.py
kleborate/modules/enterobacterales__species/test_enterobacterales__species.py
kleborate/modules/enterobacterales__species/data/species_mash_sketches.msh
kleborate/modules/escherichia__amr/__init__.py
kleborate/modules/escherichia__amr/escherichia__amr.py
kleborate/modules/escherichia__ectyper/__init__.py
kleborate/modules/escherichia__ectyper/ectyper.py
kleborate/modules/escherichia__ectyper/escherichia__ectyper.py
kleborate/modules/escherichia__ectyper/data/ectyper_alleles_db.fasta
kleborate/modules/escherichia__ectyper/data/ectyper_alleles_db.json
kleborate/modules/escherichia__ezclermont/__init__.py
kleborate/modules/escherichia__ezclermont/escherichia__ezclermont.py
kleborate/modules/escherichia__mlst_achtman/__init__.py
kleborate/modules/escherichia__mlst_achtman/escherichia__mlst_achtman.py
kleborate/modules/escherichia__mlst_achtman/test_escherichia__mlst_achtman.py
kleborate/modules/escherichia__mlst_achtman/data/adk.fasta
kleborate/modules/escherichia__mlst_achtman/data/download.sh
kleborate/modules/escherichia__mlst_achtman/data/fumC.fasta
kleborate/modules/escherichia__mlst_achtman/data/gyrB.fasta
kleborate/modules/escherichia__mlst_achtman/data/icd.fasta
kleborate/modules/escherichia__mlst_achtman/data/mdh.fasta
kleborate/modules/escherichia__mlst_achtman/data/profiles.tsv
kleborate/modules/escherichia__mlst_achtman/data/purA.fasta
kleborate/modules/escherichia__mlst_achtman/data/recA.fasta
kleborate/modules/escherichia__mlst_lee/__init__.py
kleborate/modules/escherichia__mlst_lee/escherichia__mlst_lee.py
kleborate/modules/escherichia__mlst_lee/data/eae.fasta
kleborate/modules/escherichia__mlst_lee/data/espA.fasta
kleborate/modules/escherichia__mlst_lee/data/espB.fasta
kleborate/modules/escherichia__mlst_lee/data/espD.fasta
kleborate-3.2.4.dist-info/licenses/LICENSE
kleborate-3.2.4.dist-info/METADATA
kleborate-3.2.4.dist-info/WHEEL
kleborate-3.2.4.dist-info/entry_points.txt
kleborate-3.2.4.dist-info/top_level.txt
kleborate-3.2.4.dist-info/RECORD
