Metadata-Version: 2.4
Name: kleborate
Version: 3.2.4
Summary: Kleborate: a tool for typing and screening pathogen genome assemblies
Author-email: Mary Maranga <gathonimaranga@gmail.com>, Ryan Wick <rrwick@gmail.com>, Kathryn Holt <kat.holt@lshtm.ac.uk>
License:                     GNU GENERAL PUBLIC LICENSE
Project-URL: homepage, https://github.com/klebgenomics/Kleborate
Project-URL: documentation, https://kleborate.readthedocs.io/
Project-URL: repository, https://github.com/klebgenomics/Kleborate
Classifier: Development Status :: 4 - Beta
Classifier: License :: OSI Approved :: GNU General Public License v3 (GPLv3)
Classifier: Programming Language :: Python :: 3
Classifier: Topic :: Scientific/Engineering :: Bio-Informatics
Classifier: Topic :: Scientific/Engineering :: Medical Science Apps.
Classifier: Intended Audience :: Science/Research
Requires-Python: >=3.9
License-File: LICENSE
Requires-Dist: biopython
Requires-Dist: numpy
Requires-Dist: dna_features_viewer
Requires-Dist: kaptive
Requires-Dist: mash
Provides-Extra: test
Requires-Dist: pytest; extra == "test"
Requires-Dist: pytest-mock; extra == "test"
Dynamic: license-file
